LICENSE
README.md
setup.py
openiva/__init__.py
openiva.egg-info/PKG-INFO
openiva.egg-info/SOURCES.txt
openiva.egg-info/dependency_links.txt
openiva.egg-info/requires.txt
openiva.egg-info/top_level.txt
openiva/commons/__init__.py
openiva/commons/data_dict.py
openiva/commons/generators.py
openiva/commons/io.py
openiva/commons/facial/__init__.py
openiva/commons/facial/database.py
openiva/commons/facial/embedding.py
openiva/commons/facial/info.py
openiva/commons/videocoding/__init__.py
openiva/commons/videocoding/decoding.py
openiva/commons/videocoding/info.py
openiva/engines/__init__.py
openiva/engines/base.py
openiva/engines/engine_ort.py
openiva/models/__init__.py
openiva/models/base.py
openiva/models/group.py
openiva/models/alignment/__init__.py
openiva/models/alignment/model.py
openiva/models/alignment/model_loop.py
openiva/models/arcface/__init__.py
openiva/models/arcface/model.py
openiva/models/arcface/utils.py
openiva/models/detector/__init__.py
openiva/models/detector/model.py
openiva/models/yolov4/__init__.py
openiva/models/yolov4/model.py
openiva/models/yolov4/utils.py
openiva/models/yolox/__init__.py
openiva/models/yolox/model.py
openiva/models/yolox/utils.py
openiva/tools/__init__.py
openiva/tools/register_face.py
openiva/tools/spider_douban.py
openiva/workers/__init__.py
openiva/workers/base.py
openiva/workers/compute.py
openiva/workers/data.py