Metadata-Version: 2.1
Name: openiva
Version: 0.0.1
Summary: An end-to-end intelligent vision analytics development toolkit based on different inference backend
Home-page: https://github.com/QuantumLiu
Author: QuantumLiu
Author-email: quantumliu@pku.edu.cn
License: UNKNOWN
Platform: UNKNOWN
License-File: LICENSE
